{
  "pass": false,
  "reviews": {
    "ParameterChecker": {
      "pass": true,
      "severity": "info",
      "issues": [],
      "recommendations": [
        "模型参数、初始条件及拓扑结构完全符合需求，热力学平衡约束与Smith预估补偿逻辑实现正确，状态变量均正确设置了fixed=true，无需修改。"
      ]
    },
    "EquationChecker": {
      "pass": true,
      "severity": "info",
      "issues": [],
      "recommendations": []
    },
    "ComponentChecker": {
      "pass": false,
      "severity": "critical",
      "issues": [
        {
          "title": "信号源基准错位违反红线",
          "detail": "参考温度阶跃信号源 step_ref 的 offset 参数设置为 0，但被控物理量的初始状态为环境温度 T0 (20.0°C)。这违反了信号源基准对齐红线，导致系统在 t=0 时刻之前处于错误的参考坐标系（0°C而非20°C），引发非预期的基准滑移。",
          "evidence": "step_ref(offset = 0)"
        },
        {
          "title": "纯延迟组件初始历史状态错位",
          "detail": "被控对象和内部模型的纯延迟组件（delay_plant 和 delay_model）未显式指定 y_start 参数，默认值为 0。由于系统在 t=0 时刻前已处于 20.0°C 的稳态，延迟模块在 t=0~10s 期间输出的历史温度将非物理地跌落至 0°C，严重破坏 Smith 预估器的补偿逻辑和初始平衡。",
          "evidence": "delay_plant(y_start = 0), delay_model(y_start = 0)"
        }
      ],
      "recommendations": [
        "将 step_ref 的 offset 修改为 T0，同时将 height 修改为 T_ref - T0，以确保基准对齐且产生正确的阶跃激励：\nModelica.Blocks.Sources.Step step_ref(height = T_ref - T0, offset = T0, startTime = 0);",
        "为 delay_plant 和 delay_model 显式指定初始输出 y_start 为 T0，以确保延迟模块在初始延迟区间内输出正确的稳态历史值：\nModelica.Blocks.Nonlinear.FixedDelay delay_plant(delayTime = L, y_start = T0);\nModelica.Blocks.Nonlinear.FixedDelay delay_model(delayTime = L, y_start = T0);"
      ]
    }
  }
}